{"commitInfo":{"timestamp":1774939950175,"operation":"WRITE","operationParameters":{"mode":"Overwrite","partitionBy":"[]"},"isolationLevel":"Serializable","isBlindAppend":false,"operationMetrics":{"numFiles":"1","numOutputRows":"2","numOutputBytes":"1044"},"engineInfo":"Apache-Spark/3.5.7 Delta-Lake/3.2.0","txnId":"fc8da982-4548-4e70-9d18-d28197673594"}}
{"metaData":{"id":"a51e6dec-e403-4bf0-8c3c-955cf403f7d5","format":{"provider":"parquet","options":{}},"schemaString":"{\"type\":\"struct\",\"fields\":[{\"name\":\"vehicle_id\",\"type\":\"string\",\"nullable\":true,\"metadata\":{}},{\"name\":\"avg_speed\",\"type\":\"double\",\"nullable\":true,\"metadata\":{}},{\"name\":\"trip_count\",\"type\":\"long\",\"nullable\":true,\"metadata\":{}}]}","partitionColumns":[],"configuration":{},"createdTime":1774939924914}}
{"protocol":{"minReaderVersion":1,"minWriterVersion":2}}
{"add":{"path":"part-00000-cc133612-7e0a-4820-8be1-2230f4321de2-c000.snappy.parquet","partitionValues":{},"size":1044,"modificationTime":1774939949290,"dataChange":true,"stats":"{\"numRecords\":2,\"minValues\":{\"vehicle_id\":\"HV0003\",\"avg_speed\":39.89869720371068,\"trip_count\":12801},\"maxValues\":{\"vehicle_id\":\"HV0005\",\"avg_speed\":39.992646944114746,\"trip_count\":37199},\"nullCount\":{\"vehicle_id\":0,\"avg_speed\":0,\"trip_count\":0}}"}}
